[{"EventType":"AirplaneEvent","TotalSum":1600.0,"SplitType":"EQUAL","Payed_by":"Linda;Salami","Payment_splits":[{}]},{"EventType":"TaxiEvent","TotalSum":15.0,"SplitType":"EQUAL","Payed_by":"Usman;Shani","Payment_splits":[{}]},{"EventType":"CinemaEvent","TotalSum":70.0,"SplitType":"UNEQUAL","Payed_by":"Vladimir;Kukharuk","Payment_splits":[{"Vladimir;The Admin":35.0,"Homeless;Dingus":9.8,"Vladimir;Kukharuk":0.0,"Usman;Shani":14.0,"Usman;The Admin":0.0,"Linda;Salami":0.0,"Hello;Fresh":11.200000000000001}]},{"EventType":"OtherEvent","TotalSum":56.0,"SplitType":"EQUAL","Payed_by":"Homeless;Dingus","Payment_splits":[{"Vladimir;The Admin":-8.0,"Homeless;Dingus":48.0,"Vladimir;Kukharuk":-8.0,"Usman;Shani":-8.0,"Usman;The Admin":-8.0,"Linda;Salami":-8.0,"Hello;Fresh":-8.0}]}]